n_is_python/__init__.py
n_is_python/n_is.py
n_is_python/polyshapes.py
n_is_python/music/Clair_de_lune_(Claude_Debussy)_Suite_bergamasque.ogg
n_is_python/music/tetris-theme-korobeiniki-arranged-for-piano-186249.mp3
n_is_python/music/tetris-theme-korobeiniki-rearranged-arr-for-music-box-184978.mp3
n_is_python/music/tetris-theme-korobeiniki-rearranged-arr-for-strings-185592.mp3
n_is_python-0.1.6.dist-info/METADATA
n_is_python-0.1.6.dist-info/WHEEL
n_is_python-0.1.6.dist-info/entry_points.txt
n_is_python-0.1.6.dist-info/licenses/LICENSE
n_is_python-0.1.6.dist-info/licenses/LICENSE-MUSIC
n_is_python-0.1.6.dist-info/licenses/LICENSE-MUSIC
n_is_python-0.1.6.dist-info/RECORD
