Metadata-Version: 2.4
Name: n_is_python
Version: 0.1.6
Summary: N-is is a terminal-based puzzle game that generalizes the classic Tetris concept to work with polyominos and polykings of any size from 1 to 6 blocks. Play traditional Tetris (4 blocks) or experiment with Tris (3 blocks), Dis (2 blocks), Pentis (5 blocks), or even Hexis (6 blocks)!
Project-URL: Homepage, https://github.com/Jakub314159265/n-is
Project-URL: Issues, https://github.com/Jakub314159265/n-is/issues
Author-email: Dear_satan <jakubj1406@gmail.com>
License-Expression: MIT
License-File: LICENSE
License-File: LICENSE-MUSIC
License-File: LICENSE-MUSIC
Classifier: Operating System :: OS Independent
Classifier: Programming Language :: Python :: 3
Requires-Python: >=3.9
Requires-Dist: numpy
Requires-Dist: pygame
